magic_admin/__init__.py
magic_admin/config.py
magic_admin/error.py
magic_admin/http_client.py
magic_admin/magic.py
magic_admin/response.py
magic_admin/version.py
magic_admin/resources/__init__.py
magic_admin/resources/base.py
magic_admin/resources/token.py
magic_admin/resources/user.py
magic_admin/resources/wallet.py
magic_admin/utils/__init__.py
magic_admin/utils/did_token.py
magic_admin/utils/http.py
magic_admin/utils/time.py
cool_magic_admin-1.2.1.dist-info/LICENSE.txt
cool_magic_admin-1.2.1.dist-info/METADATA
cool_magic_admin-1.2.1.dist-info/WHEEL
cool_magic_admin-1.2.1.dist-info/top_level.txt
cool_magic_admin-1.2.1.dist-info/RECORD
