Metadata-Version: 2.1
Name: cool-magic-admin
Version: 1.2.1
Summary: Magic Python Library Revised to support python versions 3.9 and above.
Home-page: https://magic.link
Author: Magic
Author-email: support@magic.link
License: MIT
Project-URL: Website, https://magic.link
Keywords: magic python sdk
Classifier: Development Status :: 3 - Alpha
Classifier: Programming Language :: Python
Classifier: Programming Language :: Python :: 3.11
Classifier: Intended Audience :: Developers
Classifier: License :: OSI Approved :: MIT License
Classifier: Operating System :: OS Independent
Requires-Python: >=3.7
License-File: LICENSE.txt
Requires-Dist: requests <3,>=2.22.0
Requires-Dist: web3 >=6
Requires-Dist: websockets >=10.0
